README.md
setup.py
d2ltorch/__init__.py
d2ltorch/utils.py
d2ltorch.egg-info/PKG-INFO
d2ltorch.egg-info/SOURCES.txt
d2ltorch.egg-info/dependency_links.txt
d2ltorch.egg-info/requires.txt
d2ltorch.egg-info/top_level.txt
d2ltorch.egg-info/zip-safe